LineAuthGPT/UnlimitedGPT.py
LineAuthGPT/__init__.py
LineAuthGPT/internal/chromedriver.exe
LineAuthGPT/internal/driver.py
LineAuthGPT/internal/exceptions.py
LineAuthGPT/internal/objects.py
LineAuthGPT/internal/selectors.py
LineAuthGPT-0.0.5.dist-info/LICENSE
LineAuthGPT-0.0.5.dist-info/METADATA
LineAuthGPT-0.0.5.dist-info/WHEEL
LineAuthGPT-0.0.5.dist-info/top_level.txt
LineAuthGPT-0.0.5.dist-info/RECORD
