Metadata-Version: 2.1
Name: LineAuthGPT
Version: 0.0.5
Summary: An unofficial Python wrapper for OpenAI's ChatGPT API
Home-page: https://github.com/linechengchen/LineAuthGPT
Author: line_defult
License: GPL-3.0 license
Project-URL: Documentation, https://github.com/linechengchen/LineAuthGPT/blob/main/README.md
Project-URL: Issue tracker, https://github.com/linechengchen/LineAuthGPT/issues
Project-URL: Changelog, https://github.com/linechengchen/LineAuthGPT/blob/main/CHANGELOG.md
Classifier: Development Status :: 5 - Production/Stable
Classifier: License :: OSI Approved :: GNU General Public License v3 (GPLv3)
Classifier: Intended Audience :: Developers
Classifier: Natural Language :: English
Classifier: Operating System :: OS Independent
Classifier: Programming Language :: Python :: 3.8
Classifier: Programming Language :: Python :: 3.9
Classifier: Programming Language :: Python :: 3.10
Classifier: Topic :: Internet
Classifier: Topic :: Software Development :: Libraries
Classifier: Topic :: Software Development :: Libraries :: Python Modules
Classifier: Topic :: Utilities
Classifier: Typing :: Typed
Requires-Python: >=3.8.0
License-File: LICENSE
Requires-Dist: undetected-chromedriver (==3.4.5)
Requires-Dist: selenium (==4.9.1)
Requires-Dist: PyVirtualDisplay (==3.0)
Requires-Dist: pyperclip
